boundvor/__init__.py
boundvor/geometry.py
boundvor/voronoi.py
boundvor-0.1.1.dist-info/LICENSE
boundvor-0.1.1.dist-info/METADATA
boundvor-0.1.1.dist-info/WHEEL
boundvor-0.1.1.dist-info/top_level.txt
boundvor-0.1.1.dist-info/RECORD
