Metadata-Version: 2.1
Name: boundvor
Version: 0.1.1
Summary: Bounded Voronoi diagram in Python
Author-email: Albert Alonso <alonfnt@pm.me>
License: MIT License
Project-URL: Homepage, https://github.com/alonfnt/boundvor
Project-URL: Documentation, https://github.com/alonfnt/boundvor
Project-URL: Source, https://github.com/alonfnt/boundvor
Project-URL: Bug Tracker, https://github.com/alonfnt/boundvor/issues
Classifier: Intended Audience :: Developers
Classifier: Intended Audience :: Science/Research
Classifier: Topic :: Scientific/Engineering
Classifier: License :: OSI Approved :: MIT License
Classifier: Programming Language :: Python :: 3
Classifier: Programming Language :: Python :: 3.9
Classifier: Programming Language :: Python :: 3.10
Classifier: Programming Language :: Python :: 3.11
License-File: LICENSE
Requires-Dist: numpy
Requires-Dist: scipy
